billbeeapi/__init__.py
billbeeapi/api_helper.py
billbeeapi/billbeeapi_client.py
billbeeapi/configuration.py
billbeeapi/decorators.py
billbeeapi/controllers/__init__.py
billbeeapi/controllers/base_controller.py
billbeeapi/controllers/cloud_storage_controller.py
billbeeapi/controllers/customer_addresses_controller.py
billbeeapi/controllers/customers_controller.py
billbeeapi/controllers/enum_api_controller.py
billbeeapi/controllers/events_controller.py
billbeeapi/controllers/orders_controller.py
billbeeapi/controllers/products_controller.py
billbeeapi/controllers/provisioning_controller.py
billbeeapi/controllers/shipments_controller.py
billbeeapi/controllers/webhooks_controller.py
billbeeapi/exceptions/__init__.py
billbeeapi/exceptions/api_exception.py
billbeeapi/http/__init__.py
billbeeapi/http/http_call_back.py
billbeeapi/http/http_client.py
billbeeapi/http/http_method_enum.py
billbeeapi/http/http_request.py
billbeeapi/http/http_response.py
billbeeapi/http/requests_client.py
billbeeapi/http/auth/__init__.py
billbeeapi/http/auth/basic_auth.py
billbeeapi/models/__init__.py
billbeeapi/models/address_type_enum.py
billbeeapi/models/article_title_source_enum.py
billbeeapi/models/billbee_interfaces_billbee_api_model_article_api_custom_field_definition_model.py
billbeeapi/models/billbee_interfaces_billbee_api_model_article_api_custom_field_value_model.py
billbeeapi/models/billbee_interfaces_billbee_api_model_article_api_model.py
billbeeapi/models/billbee_interfaces_billbee_api_model_article_category_api_model.py
billbeeapi/models/billbee_interfaces_billbee_api_model_article_image_relation_api_model.py
billbeeapi/models/billbee_interfaces_billbee_api_model_article_source_api_model.py
billbeeapi/models/billbee_interfaces_billbee_api_model_bom_sub_article_api_model.py
billbeeapi/models/billbee_interfaces_billbee_api_model_cloud_storage_api_model.py
billbeeapi/models/billbee_interfaces_billbee_api_model_comment_api_model.py
billbee_1-1.0.0.dist-info/LICENSE
billbee_1-1.0.0.dist-info/METADATA
billbee_1-1.0.0.dist-info/WHEEL
billbee_1-1.0.0.dist-info/top_level.txt
billbee_1-1.0.0.dist-info/RECORD
